{
  "name": "Notifiarr",
  "slug": "notifiarr",
  "categories": [
    14
  ],
  "date_created": "2024-06-12",
  "type": "ct",
  "updateable": true,
  "privileged": false,
  "interface_port": 5454,
  "documentation": "https://notifiarr.wiki/",
  "website": "https://notifiarr.com/",
  "logo": "https://cdn.jsdelivr.net/gh/selfhst/icons@main/webp/notifiarr.webp",
  "config_path": "/etc/notifiarr/notifiarr.conf",
  "description": "Notifiarr 是一个专门构建的系统，用于将许多应用程序整合在一起，通过 Discord 管理和自定义通知。您可以监控网络的许多方面，接收停机通知、健康问题通知等",
  "install_methods": [
    {
      "type": "default",
      "script": "ct/notifiarr.sh",
      "resources": {
        "cpu": 1,
        "ram": 512,
        "hdd": 2,
        "os": "debian",
        "version": "13"
      }
    }
  ],
  "default_credentials": {
    "username": null,
    "password": null
  },
  "notes": [
    {
      "text": "Manually edit `/etc/notifiarr/notifiarr.conf`to enter the API key from Notifiarr.com, and create a password for the UI.",
      "type": "info"
    }
  ]
}
