{
  "name": "Tdarr",
  "slug": "tdarr",
  "categories": [
    14
  ],
  "date_created": "2024-05-02",
  "type": "ct",
  "updateable": true,
  "privileged": false,
  "interface_port": 8265,
  "documentation": "https://docs.tdarr.io/docs/welcome/what",
  "website": "https://tdarr.io/",
  "logo": "https://cdn.jsdelivr.net/gh/selfhst/icons@main/webp/tdarr.webp",
  "config_path": "",
  "description": "Tdarr 是一个媒体转码应用程序,旨在自动化媒体库的转码和重新封装管理。它使用基于条件的处理来确定库中每个文件所需的编码和重新封装操作。该软件与流行的媒体管理工具(如 Sonarr 和 Radarr)集成,以确保新添加的媒体文件自动处理并针对用户所需的播放设备进行优化。Tdarr 提供基于 Web 的界面用于监控和管理转码过程,还支持实时日志记录和报告。该软件设计灵活且可配置,为用户提供广泛的编码和重新封装选项。Tdarr 是媒体爱好者的理想解决方案,他们希望优化其库以在各种设备上无缝播放,同时简化媒体库的管理和维护。",
  "install_methods": [
    {
      "type": "default",
      "script": "ct/tdarr.sh",
      "resources": {
        "cpu": 2,
        "ram": 2048,
        "hdd": 4,
        "os": "debian",
        "version": "13"
      }
    }
  ],
  "default_credentials": {
    "username": null,
    "password": null
  },
  "notes": [
    {
      "text": "With Privileged/Unprivileged Hardware Acceleration Support",
      "type": "info"
    }
  ]
}
